[
   {
      "status_text" : "發電運轉",
      "power" : 634,
      "machine" : "核一廠一號機",
      "status" : 0,
      "ratio" : 100,
      "localtime" : "2014-06-29T12:19:55+08"
   },
   {
      "power" : 646,
      "status_text" : "發電運轉",
      "localtime" : "2014-06-29T12:19:55+08",
      "machine" : "核一廠二號機",
      "status" : 0,
      "ratio" : 100
   },
   {
      "machine" : "核二廠一號機",
      "ratio" : 100,
      "status" : 0,
      "localtime" : "2014-06-29T12:19:55+08",
      "status_text" : "發電運轉",
      "power" : 1006
   },
   {
      "power" : 1009,
      "status_text" : "發電運轉",
      "localtime" : "2014-06-29T12:19:55+08",
      "machine" : "核二廠二號機",
      "ratio" : 100,
      "status" : 0
   },
   {
      "ratio" : 100,
      "status" : 0,
      "machine" : "核三廠一號機",
      "localtime" : "2014-06-29T12:19:55+08",
      "status_text" : "發電運轉",
      "power" : 969
   },
   {
      "power" : 973,
      "status_text" : "發電運轉",
      "localtime" : "2014-06-29T12:19:55+08",
      "machine" : "核三廠二號機",
      "status" : 0,
      "ratio" : 100
   }
]
