[
   {
      "machine" : "核一廠一號機",
      "status" : 0,
      "localtime" : "2014-10-14T09:50:12+08",
      "ratio" : 100,
      "status_text" : "發電運轉",
      "power" : 647
   },
   {
      "status" : 0,
      "machine" : "核一廠二號機",
      "localtime" : "2014-10-14T09:50:12+08",
      "ratio" : 100,
      "status_text" : "發電運轉",
      "power" : 651
   },
   {
      "localtime" : "2014-10-14T09:50:12+08",
      "machine" : "核二廠一號機",
      "status" : 0,
      "power" : 1015,
      "ratio" : 100,
      "status_text" : "發電運轉"
   },
   {
      "ratio" : 1,
      "status_text" : "機組大修",
      "power" : 0,
      "status" : 1,
      "machine" : "核二廠二號機",
      "localtime" : "2014-10-14T09:50:12+08"
   },
   {
      "status_text" : "發電運轉",
      "ratio" : 100,
      "power" : 979,
      "status" : 0,
      "machine" : "核三廠一號機",
      "localtime" : "2014-10-14T09:50:12+08"
   },
   {
      "localtime" : "2014-10-14T09:50:12+08",
      "machine" : "核三廠二號機",
      "status" : 0,
      "power" : 737,
      "ratio" : 78,
      "status_text" : "發電運轉"
   }
]
