[
   {
      "localtime" : "2014-06-04T17:33:10+08",
      "power" : 643,
      "status" : 0,
      "status_text" : "發電運轉",
      "ratio" : 100,
      "machine" : "核一廠一號機"
   },
   {
      "localtime" : "2014-06-04T17:33:10+08",
      "power" : 263,
      "status" : 0,
      "status_text" : "發電運轉",
      "ratio" : 47,
      "machine" : "核一廠二號機"
   },
   {
      "ratio" : 100,
      "machine" : "核二廠一號機",
      "localtime" : "2014-06-04T17:33:10+08",
      "power" : 1012,
      "status_text" : "發電運轉",
      "status" : 0
   },
   {
      "localtime" : "2014-06-04T17:33:10+08",
      "power" : 1014,
      "status" : 0,
      "status_text" : "發電運轉",
      "ratio" : 100,
      "machine" : "核二廠二號機"
   },
   {
      "power" : 978,
      "status_text" : "發電運轉",
      "status" : 0,
      "localtime" : "2014-06-04T17:33:10+08",
      "ratio" : 100,
      "machine" : "核三廠一號機"
   },
   {
      "status_text" : "發電運轉",
      "status" : 0,
      "power" : 977,
      "localtime" : "2014-06-04T17:33:10+08",
      "machine" : "核三廠二號機",
      "ratio" : 100
   }
]
