[
   {
      "localtime" : "2014-06-04T22:14:13+08",
      "status" : 0,
      "machine" : "核一廠一號機",
      "status_text" : "發電運轉",
      "power" : 638,
      "ratio" : 100
   },
   {
      "ratio" : 70,
      "power" : 433,
      "status_text" : "發電運轉",
      "status" : 0,
      "machine" : "核一廠二號機",
      "localtime" : "2014-06-04T22:14:13+08"
   },
   {
      "status" : 0,
      "localtime" : "2014-06-04T22:14:13+08",
      "machine" : "核二廠一號機",
      "ratio" : 100,
      "power" : 1010,
      "status_text" : "發電運轉"
   },
   {
      "power" : 1015,
      "ratio" : 100,
      "status_text" : "發電運轉",
      "status" : 0,
      "machine" : "核二廠二號機",
      "localtime" : "2014-06-04T22:14:13+08"
   },
   {
      "status" : 0,
      "localtime" : "2014-06-04T22:14:13+08",
      "machine" : "核三廠一號機",
      "ratio" : 100,
      "power" : 977,
      "status_text" : "發電運轉"
   },
   {
      "power" : 977,
      "ratio" : 100,
      "status_text" : "發電運轉",
      "status" : 0,
      "localtime" : "2014-06-04T22:14:13+08",
      "machine" : "核三廠二號機"
   }
]
