[
   {
      "power" : 655,
      "status" : 0,
      "ratio" : 100,
      "localtime" : "2014-12-08T04:59:57+08",
      "machine" : "核一廠一號機",
      "status_text" : "發電運轉"
   },
   {
      "localtime" : "2014-12-08T04:59:57+08",
      "power" : 658,
      "ratio" : 100,
      "status" : 0,
      "status_text" : "發電運轉",
      "machine" : "核一廠二號機"
   },
   {
      "localtime" : "2014-12-08T04:59:57+08",
      "status" : 0,
      "power" : 943,
      "ratio" : 92,
      "status_text" : "發電運轉",
      "machine" : "核二廠一號機"
   },
   {
      "machine" : "核二廠二號機",
      "status_text" : "發電運轉",
      "power" : 1026,
      "ratio" : 100,
      "status" : 0,
      "localtime" : "2014-12-08T04:59:57+08"
   },
   {
      "localtime" : "2014-12-08T04:59:57+08",
      "status" : 0,
      "power" : 977,
      "ratio" : 100,
      "status_text" : "發電運轉",
      "machine" : "核三廠一號機"
   },
   {
      "localtime" : "2014-12-08T04:59:57+08",
      "power" : 981,
      "ratio" : 100,
      "status" : 0,
      "status_text" : "發電運轉",
      "machine" : "核三廠二號機"
   }
]
