[
   {
      "power" : 641,
      "status_text" : "發電運轉",
      "machine" : "核一廠一號機",
      "ratio" : 100,
      "localtime" : "2014-06-29T09:02:54+08",
      "status" : 0
   },
   {
      "power" : 647,
      "status_text" : "發電運轉",
      "ratio" : 100,
      "machine" : "核一廠二號機",
      "localtime" : "2014-06-29T09:02:54+08",
      "status" : 0
   },
   {
      "status" : 0,
      "localtime" : "2014-06-29T09:02:54+08",
      "power" : 1013,
      "status_text" : "發電運轉",
      "ratio" : 100,
      "machine" : "核二廠一號機"
   },
   {
      "localtime" : "2014-06-29T09:02:54+08",
      "power" : 1017,
      "status_text" : "發電運轉",
      "ratio" : 100,
      "machine" : "核二廠二號機",
      "status" : 0
   },
   {
      "status" : 0,
      "localtime" : "2014-06-29T09:02:54+08",
      "machine" : "核三廠一號機",
      "status_text" : "發電運轉",
      "power" : 975,
      "ratio" : 100
   },
   {
      "status_text" : "發電運轉",
      "ratio" : 100,
      "power" : 972,
      "machine" : "核三廠二號機",
      "localtime" : "2014-06-29T09:02:54+08",
      "status" : 0
   }
]
