[
   {
      "localtime" : "2014-06-23T03:03:44+08",
      "ratio" : 100,
      "status" : 0,
      "power" : 640,
      "machine" : "核一廠一號機",
      "status_text" : "發電運轉"
   },
   {
      "machine" : "核一廠二號機",
      "status_text" : "發電運轉",
      "power" : 651,
      "ratio" : 100,
      "localtime" : "2014-06-23T03:03:44+08",
      "status" : 0
   },
   {
      "ratio" : 91,
      "localtime" : "2014-06-23T03:03:44+08",
      "status" : 0,
      "power" : 917,
      "machine" : "核二廠一號機",
      "status_text" : "發電運轉"
   },
   {
      "localtime" : "2014-06-23T03:03:44+08",
      "ratio" : 100,
      "status" : 0,
      "power" : 1011,
      "status_text" : "發電運轉",
      "machine" : "核二廠二號機"
   },
   {
      "status_text" : "發電運轉",
      "machine" : "核三廠一號機",
      "power" : 973,
      "localtime" : "2014-06-23T03:03:44+08",
      "ratio" : 100,
      "status" : 0
   },
   {
      "power" : 974,
      "machine" : "核三廠二號機",
      "status_text" : "發電運轉",
      "localtime" : "2014-06-23T03:03:44+08",
      "ratio" : 100,
      "status" : 0
   }
]
