[
   {
      "machine" : "核一廠一號機",
      "status_text" : "發電運轉",
      "localtime" : "2014-10-18T03:36:23+08",
      "status" : 0,
      "power" : 651,
      "ratio" : 100
   },
   {
      "power" : 654,
      "ratio" : 100,
      "machine" : "核一廠二號機",
      "status_text" : "發電運轉",
      "localtime" : "2014-10-18T03:36:23+08",
      "status" : 0
   },
   {
      "ratio" : 100,
      "power" : 1018,
      "machine" : "核二廠一號機",
      "status_text" : "發電運轉",
      "localtime" : "2014-10-18T03:36:23+08",
      "status" : 0
   },
   {
      "ratio" : 68,
      "power" : 651,
      "status" : 0,
      "localtime" : "2014-10-18T03:36:23+08",
      "status_text" : "發電運轉",
      "machine" : "核二廠二號機"
   },
   {
      "status" : 0,
      "localtime" : "2014-10-18T03:36:23+08",
      "status_text" : "發電運轉",
      "machine" : "核三廠一號機",
      "power" : 978,
      "ratio" : 100
   },
   {
      "localtime" : "2014-10-18T03:36:23+08",
      "status" : 0,
      "status_text" : "發電運轉",
      "machine" : "核三廠二號機",
      "ratio" : 78,
      "power" : 751
   }
]
