[
   {
      "area" : "基隆市成功一路、獅球路、光一、二路、華一、二、三、四、五、六街(含各巷弄)全部停水",
      "interval_from" : "2014-3-5T10:00+08",
      "interval_until" : "2014-3-5T17:00+08",
      "publish_area" : "200基隆市仁愛區",
      "publish_duration" : "2014-02-27/2015-03-05",
      "publish_from" : "2014-02-27",
      "publish_until" : "2015-03-05",
      "telephone" : "(02)24234195基隆服務所"
   },
   {
      "area" : "湖口鄉東興村中山路二、三段、和興村，新豐鄉福興村、後湖村全部地區，及湖口鄉德盛村部份地區停水。",
      "interval_from" : "2014-5-19T00+08",
      "interval_until" : "2014-5-23T止(每日上午9:至下午17時施工停水，下午17時後恢復供水)。+08",
      "publish_area" : "303新竹縣湖口鄉     304新竹縣新豐鄉",
      "publish_duration" : "2014-05-13/2014-05-27",
      "publish_from" : "2014-05-13",
      "publish_until" : "2014-05-27",
      "telephone" : "1910、湖口營運所03-5981603"
   },
   {
      "area" : "通霄鎮(通灣、通東、通西、平元、平安、梅南、城南、城北、圳頭、內湖、烏眉、楓樹等里)。",
      "interval_from" : "2014-5-27T13:00+08",
      "interval_until" : "2014-5-27T19:00+08",
      "publish_area" : "357苗栗縣通霄鎮",
      "publish_duration" : "2014-05-20/2014-05-29",
      "publish_from" : "2014-05-20",
      "publish_until" : "2014-05-29",
      "telephone" : "1910、通霄銅鑼營運所：037-986206"
   },
   {
      "area" : "竹南鎮部分：竹南里、照南里、正南里、新南里、營盤里、大厝里、聖福里、竹興里、山佳里、龍鳳里、中港里、中華里、中英里、中美里、開元里、海口里、天文里、港漧里、龍山里、大埔里、佳興里、崎頂里等。<BR>頭份鎮部份：田寮里。<BR>",
      "interval_from" : "2014-5-29T08:00+08",
      "interval_until" : "2014-5-29T19:00+08",
      "publish_area" : "350苗栗縣竹南鎮     351苗栗縣頭份鎮",
      "publish_duration" : "2014-05-20/2014-05-29",
      "publish_from" : "2014-05-20",
      "publish_until" : "2014-05-29",
      "telephone" : "1910、東興給水廠：037-669621、竹南頭份營運所：037-623500"
   },
   {
      "area" : "湖口鄉東興村中山路二、三段、和興村及新豐鄉福興村、後湖村全部地區及湖口鄉德盛村部份地區停水<BR>",
      "interval_from" : "2014-5-28T00+08",
      "interval_until" : "2014-5-30T止(每日上午9:至下午17時施工停水，下午17時後恢復供水)。+08",
      "publish_area" : "303新竹縣湖口鄉",
      "publish_duration" : "2014-05-20/2014-06-03",
      "publish_from" : "2014-05-20",
      "publish_until" : "2014-06-03",
      "telephone" : "1910、湖口營運所03-5981603"
   },
   {
      "area" : "基隆市成功二路、中山一、二、三、四路、健民街、華興街、仁安街、太白街、光華路、安一路、定國街、新西街、安一路、西定路、通仁街、通明街、復旦路、中華路、協和街、文化路(含各巷弄) 全部停水.",
      "interval_from" : "2013-10-16T09:00+08",
      "interval_until" : "2013-10-16T15:00+08",
      "publish_area" : "203基隆市中山區",
      "publish_duration" : "2014-10-09/2014-10-16",
      "publish_from" : "2014-10-09",
      "publish_until" : "2014-10-16",
      "telephone" : "02-24245200"
   },
   {
      "area" : "【區域1】新北市林口區103年2月10日至103年3月31日(每日上午8時至下午18時):工四路及工五路(約100戶)。;103年4月1日至103年4月18日(每日上午8時至下午18時):工二路及工三路(約50戶)。;103年4月21日至103年5月19日(每日上午8時至下午18時):工七路及工八路(約50戶)。;103年5月20日至103年6月5日(每日上午8時至下午18時):粉寮路一段(約30戶)。",
      "interval_comment" : "(每日上午8時至下午18時)",
      "interval_from" : "2014-02-10T08:00+08",
      "interval_until" : "2014-06-05T18:00+08",
      "publish_area" : "244新北市林口區",
      "publish_duration" : "2014-01-17/2014-06-06",
      "publish_from" : "2014-01-17",
      "publish_until" : "2014-06-06",
      "telephone" : "免付費服務電話：1910  林口服務所:02-26030522"
   },
   {
      "area" : "【區域1】南投縣埔里鎮鐵山里、愛蘭里",
      "interval_comment" : "每日上午9點至下午6點(六日不施工)",
      "interval_from" : "2014-02-25T09:00+08",
      "interval_until" : "2014-09-30T18:00+08",
      "publish_area" : "545南投縣埔里鎮",
      "publish_duration" : "2014-02-25/2014-10-01",
      "publish_from" : "2014-02-25",
      "publish_until" : "2014-10-01",
      "telephone" : "049-2915176"
   },
   {
      "area" : "【區域1】南投縣水里鄉二坪路",
      "interval_comment" : "每日上午8點至下午6點",
      "interval_from" : "2014-03-06T08:00+08",
      "interval_until" : "2014-05-30T18:00+08",
      "publish_area" : "553南投縣水里鄉",
      "publish_duration" : "2014-03-05/2014-05-31",
      "publish_from" : "2014-03-05",
      "publish_until" : "2014-05-31",
      "telephone" : "049-2762076"
   },
   {
      "area" : "【區域1】南投縣中寮鄉永樂路(八仙-哮貓);永平路(八仙村;福盛村;崁頂村;廣興村)等及鄰近部分地區水壓降低(約30戶)。",
      "interval_comment" : "每日上午8點30分至下午6點",
      "interval_from" : "2014-03-25T08:30+08",
      "interval_until" : "2014-07-03T18:00+08",
      "publish_area" : "541南投縣中寮鄉",
      "publish_duration" : "2014-03-14/2014-07-04",
      "publish_from" : "2014-03-14",
      "publish_until" : "2014-07-04",
      "telephone" : "0492222635;1910"
   },
   {
      "area" : "【區域1】台中市大里區東南路(中興路-大峰路)及其巷弄。",
      "interval_comment" : "上午08:30至下午17:30，提早完工隨即恢復供水。",
      "interval_from" : "2014-02-24T08:30+08",
      "interval_until" : "2014-05-31T17:30+08",
      "publish_area" : "412台中市大里區",
      "publish_duration" : "2014-03-15/2014-06-01",
      "publish_from" : "2014-03-15",
      "publish_until" : "2014-06-01",
      "telephone" : "0939867798"
   },
   {
      "area" : "【區域1】南投縣鹿谷鄉清水村;瑞田村",
      "interval_comment" : "每日上午8點至下午6點",
      "interval_from" : "2014-04-15T10:00+08",
      "interval_until" : "2014-06-15T18:00+08",
      "publish_area" : "558南投縣鹿谷鄉",
      "publish_duration" : "2014-04-15/2014-06-16",
      "publish_from" : "2014-04-15",
      "publish_until" : "2014-06-16",
      "telephone" : "0492642074"
   },
   {
      "area" : "【區域1】南投縣水里鄉頂崁村;郡坑村;鉅工村;永豐巷;圳頭巷;",
      "interval_from" : "2014-04-28T08:00+08",
      "interval_until" : "2014-06-18T18:00+08",
      "publish_area" : "553南投縣水里鄉",
      "publish_duration" : "2014-04-28/2014-06-19",
      "publish_from" : "2014-04-28",
      "publish_until" : "2014-06-19",
      "telephone" : "049-2762076"
   },
   {
      "area" : "【區域1】高雄市六龜區新寮里三民路一帶皆受影響。",
      "interval_from" : "2014-05-02T09:00+08",
      "interval_until" : "2014-05-31T17:00+08",
      "publish_area" : "844高雄市六龜區",
      "publish_duration" : "2014-05-02/2014-06-01",
      "publish_from" : "2014-05-02",
      "publish_until" : "2014-06-01",
      "telephone" : "0933688276"
   },
   {
      "area" : "【區域1】台東縣太麻里鄉大王村-大王路、加拉班街、太峰路、市隆路、文化路、至善路、利里武街、金萱路、德輝路、民權路。泰和村-2鄰民權路",
      "interval_comment" : "每日上午8點至下午6點",
      "interval_from" : "2014-05-05T08:00+08",
      "interval_until" : "2014-05-25T18:00+08",
      "publish_area" : "963台東縣太麻里鄉",
      "publish_duration" : "2014-05-05/2014-05-26",
      "publish_from" : "2014-05-05",
      "publish_until" : "2014-05-26",
      "telephone" : "089-328817   089-326122#309    0937-390925   0933-371125    0932-559811"
   },
   {
      "area" : "【區域1】彰化縣員林鎮大同路一、二段{全部}及延線巷道;三民東街;員東路二段;成功東路;正興街;明德街;浮圳路二段;實踐街;成功路;和平東街一段;和平東街;建國路;光華街;長榮街;興昌街;大同路二段;大同路一段;大勇街",
      "interval_comment" : "每日上午8點至下午6點",
      "interval_from" : "2014-05-07T09:00+08",
      "interval_until" : "2014-06-09T18:00+08",
      "publish_area" : "510彰化縣員林鎮",
      "publish_duration" : "2014-05-07/2014-06-10",
      "publish_from" : "2014-05-07",
      "publish_until" : "2014-06-10",
      "telephone" : "04-8320083"
   },
   {
      "area" : "【區域1】新北市樹林區俊英街(樹新路口至大安路口)各巷弄及千歲街",
      "interval_comment" : "每日上午9點至下午6點",
      "interval_from" : "2014-05-09T09:00+08",
      "interval_until" : "2014-06-07T18:00+08",
      "publish_area" : "238新北市樹林區",
      "publish_duration" : "2014-05-07/2014-06-08",
      "publish_from" : "2014-05-07",
      "publish_until" : "2014-06-08",
      "telephone" : "02-26812254"
   },
   {
      "area" : "【區域1】新北市林口區文化一路二段至四維路、四維路至吉林街、四維路至仁愛路、新寮路。",
      "interval_comment" : "每日上午9時至下午18時(星期六、日除外)",
      "interval_from" : "2014-05-14T09:00+08",
      "interval_until" : "2014-05-30T18:00+08",
      "publish_area" : "244新北市林口區",
      "publish_duration" : "2014-05-13/2014-05-31",
      "publish_from" : "2014-05-13",
      "publish_until" : "2014-05-31",
      "telephone" : "免付費服務電話：1910    林口服務所:02-26030522"
   },
   {
      "area" : "【區域1】台南市南化區中坑里1-50號;南化里1-40號",
      "interval_comment" : "每日上午8點至下午6點",
      "interval_from" : "2014-05-17T08:00+08",
      "interval_until" : "2014-05-31T18:00+08",
      "publish_area" : "716台南市南化區",
      "publish_duration" : "2014-05-13/2014-06-01",
      "publish_from" : "2014-05-13",
      "publish_until" : "2014-06-01",
      "telephone" : "06-5742323"
   },
   {
      "area" : "【區域1】彰化縣鹿港鎮頂番里;人和巷;埤頭巷;彰頂路",
      "interval_comment" : "08:00-17:00",
      "interval_from" : "2014-05-15T08:00+08",
      "interval_until" : "2014-05-28T17:00+08",
      "publish_area" : "505彰化縣鹿港鎮",
      "publish_duration" : "2014-05-13/2014-05-29",
      "publish_from" : "2014-05-13",
      "publish_until" : "2014-05-29",
      "telephone" : "04-7772127、047772690"
   },
   {
      "area" : "【區域1】彰化縣溪湖鎮河東里;西勢里;田中里",
      "interval_comment" : "每日上午10點至下午6點",
      "interval_from" : "2014-05-14T10:00+08",
      "interval_until" : "2014-05-31T18:00+08",
      "publish_area" : "514彰化縣溪湖鎮",
      "publish_duration" : "2014-05-14/2014-06-01",
      "publish_from" : "2014-05-14",
      "publish_until" : "2014-06-01",
      "telephone" : "8851778"
   },
   {
      "area" : "【區域1】桃園縣觀音鄉觀音工業區：工業七路、國建二路、國建三路、國瑞路、國光路、國華路。",
      "interval_from" : "2014-05-25T09:00+08",
      "interval_until" : "2014-05-25T18:00+08",
      "publish_area" : "328桃園縣觀音鄉",
      "publish_duration" : "2014-05-14/2014-05-26",
      "publish_from" : "2014-05-14",
      "publish_until" : "2014-05-26",
      "telephone" : "免付費專線:1910  大園服務所:03-3862156"
   },
   {
      "area" : "【區域1】南投縣草屯鎮中山里;中正里;北投里;玉峰里;炎峰里;復興里;敦和里;碧峰里;明正里;和平里;碧洲里;新厝里;中山里;山腳里",
      "interval_from" : "2014-03-17T15:00+08",
      "interval_until" : "2014-06-17T23:00+08",
      "publish_area" : "542南投縣草屯鎮",
      "publish_duration" : "2014-05-16/2014-06-18",
      "publish_from" : "2014-05-16",
      "publish_until" : "2014-06-18",
      "telephone" : "049-2563505.2566689"
   },
   {
      "area" : "【區域1】新北市八里區松子腳路",
      "interval_comment" : "每日上午9時00分至下午16時00分止，工程結束即恢復供水",
      "interval_from" : "2014-05-17T09:00+08",
      "interval_until" : "2014-05-26T16:00+08",
      "publish_area" : "249新北市八里區",
      "publish_duration" : "2014-05-16/2014-05-27",
      "publish_from" : "2014-05-16",
      "publish_until" : "2014-05-27",
      "telephone" : "22821817"
   },
   {
      "area" : "【區域1】嘉義縣阿里山鄉中山村;中正村;香林村",
      "interval_comment" : ":每日上午8點至下午7點",
      "interval_from" : "2014-05-16T08:00+08",
      "interval_until" : "2014-08-15T19:00+08",
      "publish_area" : "605嘉義縣阿里山鄉",
      "publish_duration" : "2014-05-16/2014-08-16",
      "publish_from" : "2014-05-16",
      "publish_until" : "2014-08-16",
      "telephone" : "05-2611075"
   },
   {
      "area" : "【區域3】台南市永康區永二街、忠孝路、復國一路、復華八街、復華十街、國華街",
      "interval_from" : "2014-05-15T10:47+08",
      "interval_until" : "2014-05-31T17:30+08",
      "publish_area" : "710台南市永康區",
      "publish_duration" : "2014-05-16/2014-06-01",
      "publish_from" : "2014-05-16",
      "publish_until" : "2014-06-01",
      "telephone" : "1910    06-2325714"
   },
   {
      "area" : "【區域1】南投縣名間鄉濁水村;新民村;中正村;南雅村等",
      "interval_from" : "2014-05-27T10:00+08",
      "interval_until" : "2014-05-27T21:00+08",
      "publish_area" : "551南投縣名間鄉",
      "publish_duration" : "2014-05-19/2014-05-28",
      "publish_from" : "2014-05-19",
      "publish_until" : "2014-05-28",
      "telephone" : "0492222635"
   },
   {
      "area" : "【區域3】南投縣南投市南投市、名間其他村、彰化縣芬園鄉大竹村、中崙村、同安村等",
      "interval_from" : "2014-05-27T10:00+08",
      "interval_until" : "2014-05-27T21:00+08",
      "publish_area" : "540南投縣南投市",
      "publish_duration" : "2014-05-19/2014-05-28",
      "publish_from" : "2014-05-19",
      "publish_until" : "2014-05-28",
      "telephone" : "0492222635"
   },
   {
      "area" : "【區域1】台中市石岡區金星里;石岡街下坑巷",
      "interval_from" : "2014-05-28T08:30+08",
      "interval_until" : "2014-05-28T18:00+08",
      "publish_area" : "422台中市石岡區",
      "publish_duration" : "2014-05-20/2014-05-29",
      "publish_from" : "2014-05-20",
      "publish_until" : "2014-05-29",
      "telephone" : ""
   },
   {
      "area" : "【區域1】台南市東區東成街1~77號(含巷弄)",
      "interval_comment" : "預計每日上午8點至下午18點 停水至18點以後恢復供水，遇雨順延",
      "interval_from" : "2014-05-06T08:00+08",
      "interval_until" : "2014-05-26T18:00+08",
      "publish_area" : "701台南市東區",
      "publish_duration" : "2014-05-20/2014-05-27",
      "publish_from" : "2014-05-20",
      "publish_until" : "2014-05-27",
      "telephone" : "朱崇輝0953888537"
   },
   {
      "area" : "【區域1】苗栗縣通霄鎮通灣里;通東里;通西里;平元里;平安里;;梅南里;城南里;城北里;圳頭里;內湖里;烏眉里;楓樹里",
      "interval_from" : "2014-05-27T13:00+08",
      "interval_until" : "2014-05-27T19:00+08",
      "publish_area" : "357苗栗縣通霄鎮",
      "publish_duration" : "2014-05-20/2014-05-28",
      "publish_from" : "2014-05-20",
      "publish_until" : "2014-05-28",
      "telephone" : "免費客服專線1910；通霄銅鑼營運所037-986206"
   },
   {
      "area" : "【區域1】高雄市岡山區路竹區玉庫里;岡山區潭底里;嘉峰里一帶停水  水壓低區域：嘉興里週遭地區一帶。(管線末端部分區域復水較晚)",
      "interval_comment" : "於5/23至5/30日每日上午10點至下午17點",
      "interval_from" : "2014-05-23T10:00+08",
      "interval_until" : "2014-05-30T17:00+08",
      "publish_area" : "820高雄市岡山區",
      "publish_duration" : "2014-05-21/2014-05-31",
      "publish_from" : "2014-05-21",
      "publish_until" : "2014-05-31",
      "telephone" : "07-6222814"
   },
   {
      "area" : "【區域3】高雄市岡山區嘉興里",
      "interval_comment" : "於5/23至5/30日每日上午10點至下午17點",
      "interval_from" : "2014-5-23T10:00+08",
      "interval_until" : "2014-5-30T17:00+08",
      "publish_area" : "820高雄市岡山區",
      "publish_duration" : "2014-05-21/2014-05-31",
      "publish_from" : "2014-05-21",
      "publish_until" : "2014-05-31",
      "telephone" : "07-6222814"
   },
   {
      "area" : "【區域1】新竹縣湖口鄉東興村中山路二 三段;和興村;德盛村部分地區;新竹縣新豐鄉福興村;後湖村",
      "interval_comment" : "每日上午9點至下午5點",
      "interval_from" : "2014-05-28T09:00+08",
      "interval_until" : "2014-05-30T17:00+08",
      "publish_area" : "303新竹縣湖口鄉     304新竹縣新豐鄉",
      "publish_duration" : "2014-05-21/2014-05-31",
      "publish_from" : "2014-05-21",
      "publish_until" : "2014-05-31",
      "telephone" : "03-5981603; 1910"
   },
   {
      "area" : "【區域1】嘉義縣竹崎鄉灣橋村;朴子埔",
      "interval_from" : "2014-06-10T08:00+08",
      "interval_until" : "2014-06-10T13:00+08",
      "publish_area" : "604嘉義縣竹崎鄉",
      "publish_duration" : "2014-05-21/2014-06-11",
      "publish_from" : "2014-05-21",
      "publish_until" : "2014-06-11",
      "telephone" : "05-2611075"
   },
   {
      "area" : "【區域1】屏東縣來義鄉丹林村",
      "interval_from" : "2014-05-21T17:30+08",
      "interval_until" : "2014-05-28T17:30+08",
      "publish_area" : "922屏東縣來義鄉",
      "publish_duration" : "2014-05-21/2014-05-29",
      "publish_from" : "2014-05-21",
      "publish_until" : "2014-05-29",
      "telephone" : "08-8325550"
   },
   {
      "area" : "【區域1】花蓮縣玉里鎮松浦里1鄰1~2號;觀音194、195、201、204號;觀音山段1109之2號",
      "interval_from" : "2014-05-28T08:00+08",
      "interval_until" : "2014-05-28T17:00+08",
      "publish_area" : "981花蓮縣玉里鎮",
      "publish_duration" : "2014-05-21/2014-05-29",
      "publish_from" : "2014-05-21",
      "publish_until" : "2014-05-29",
      "telephone" : "(03)8882403"
   },
   {
      "area" : "【區域1】嘉義市東區嘉義市短竹里小雅路100至419號",
      "interval_comment" : "正常下午6點供水，惟管線末端用戶可能因水流時間延至下午8點供水",
      "interval_from" : "2014-05-28T08:00+08",
      "interval_until" : "2014-06-06T18:00+08",
      "publish_area" : "600嘉義市東區",
      "publish_duration" : "2014-05-21/2014-06-07",
      "publish_from" : "2014-05-21",
      "publish_until" : "2014-06-07",
      "telephone" : "本案聯絡人：洪國彬 0978-060558 工地負責人：邱莊湖 行動電話：0926-785233"
   },
   {
      "area" : "【區域1】高雄市美濃區美濃地區皆受影響。",
      "interval_from" : "2014-05-20T08:00+08",
      "interval_until" : "2014-06-30T23:00+08",
      "publish_area" : "843高雄市美濃區",
      "publish_duration" : "2014-05-22/2014-07-01",
      "publish_from" : "2014-05-22",
      "publish_until" : "2014-07-01",
      "telephone" : "0928174027"
   },
   {
      "area" : "【區域1】雲林縣大埤鄉北和村;南和村",
      "interval_comment" : "每日上午8點至下午5點30分",
      "interval_from" : "2014-05-23T08:00+08",
      "interval_until" : "2014-06-05T17:30+08",
      "publish_area" : "631雲林縣大埤鄉",
      "publish_duration" : "2014-05-22/2014-06-06",
      "publish_from" : "2014-05-22",
      "publish_until" : "2014-06-06",
      "telephone" : "05-5972682"
   },
   {
      "area" : "【區域1】桃園縣大園鄉大園鄉大園工業區：民生路、民權路、民族路、潮音路、中山北路、河堤道路、內海村(全部);水壓降低地區:大園鄉:圳頭村。",
      "interval_from" : "2014-06-08T09:00+08",
      "interval_until" : "2014-06-08T18:00+08",
      "publish_area" : "337桃園縣大園鄉",
      "publish_duration" : "2014-05-22/2014-06-09",
      "publish_from" : "2014-05-22",
      "publish_until" : "2014-06-09",
      "telephone" : "免付費專線:1910  大園服務所:03-3862156"
   },
   {
      "area" : "【區域1】高雄市大社區水壓降低;高雄市大樹區義大世界一帶水壓降低;高雄市田寮區水壓降低(鹿埔里、古亭里除外);高雄市岡山區和平里水壓降低;高雄市阿蓮區水壓降低;高雄市楠梓區水壓降低;高雄市路竹區甲北里、新園里、下坑里水壓降低;高雄市燕巢區水壓降低",
      "interval_from" : "2014-05-29T10:00+08",
      "interval_until" : "2014-05-30T06:00+08",
      "publish_area" : "815高雄市大社區     840高雄市大樹區     823高雄市田寮區     820高雄市岡山區     822高雄市阿蓮區     811高雄市楠梓區     821高雄市路竹區     824高雄市燕巢區",
      "publish_duration" : "2014-05-22/2014-05-31",
      "publish_from" : "2014-05-22",
      "publish_until" : "2014-05-31",
      "telephone" : "1910"
   },
   {
      "area" : "【區域1】彰化縣田中鎮建國路全部;長順街",
      "interval_comment" : "每日上午8點至下午6點",
      "interval_from" : "2014-05-26T08:00+08",
      "interval_until" : "2014-05-31T18:00+08",
      "publish_area" : "520彰化縣田中鎮",
      "publish_duration" : "2014-05-22/2014-06-01",
      "publish_from" : "2014-05-22",
      "publish_until" : "2014-06-01",
      "telephone" : "04-8793211"
   },
   {
      "area" : "【區域1】南投縣南投市祖祠路180~340號〈雙號〉、祖祠路77巷、141巷。彰南路二段308~468號雙側〈含彰南路二段242、254、422、464、475等巷〉;竹林路;新市路;南崗二路190號至南崗三路6號、興和巷;平山一路;平山二路全部",
      "interval_from" : "2014-05-27T10:00+08",
      "interval_until" : "2014-05-27T21:00+08",
      "publish_area" : "540南投縣南投市",
      "publish_duration" : "2014-05-23/2014-05-28",
      "publish_from" : "2014-05-23",
      "publish_until" : "2014-05-28",
      "telephone" : "0492222635"
   },
   {
      "area" : "【區域1】桃園縣觀音鄉工業七路;國建二路;國建三路;國瑞路;國光路;國華路",
      "interval_from" : "2014-05-25T09:00+08",
      "interval_until" : "2014-05-25T18:00+08",
      "publish_area" : "328桃園縣觀音鄉",
      "publish_duration" : "2014-05-23/2014-05-26",
      "publish_from" : "2014-05-23",
      "publish_until" : "2014-05-26",
      "telephone" : "3862156"
   },
   {
      "area" : "【區域1】嘉義縣民雄鄉金興村金世界",
      "interval_comment" : "每日上午10點至下午7點",
      "interval_from" : "2014-05-27T10:00+08",
      "interval_until" : "2014-05-28T19:00+08",
      "publish_area" : "621嘉義縣民雄鄉",
      "publish_duration" : "2014-05-23/2014-05-29",
      "publish_from" : "2014-05-23",
      "publish_until" : "2014-05-29",
      "telephone" : "0937-355-685"
   },
   {
      "area" : "【區域1】高雄市鳳山區鳳山區華西街20號附近",
      "interval_from" : "2014-05-25T13:00+08",
      "interval_until" : "2014-05-25T17:00+08",
      "publish_area" : "830高雄市鳳山區",
      "publish_duration" : "2014-05-23/2014-05-26",
      "publish_from" : "2014-05-23",
      "publish_until" : "2014-05-26",
      "telephone" : "07-7424163"
   },
   {
      "area" : "【區域1】高雄市大寮區大寮區四維街352號附近",
      "interval_from" : "2014-05-25T08:00+08",
      "interval_until" : "2014-05-25T12:00+08",
      "publish_area" : "831高雄市大寮區",
      "publish_duration" : "2014-05-23/2014-05-26",
      "publish_from" : "2014-05-23",
      "publish_until" : "2014-05-26",
      "telephone" : "07-7424163"
   },
   {
      "area" : "【區域1】高雄市林園區林園區西溪路152號附近",
      "interval_from" : "2014-05-25T08:00+08",
      "interval_until" : "2014-05-25T12:00+08",
      "publish_area" : "832高雄市林園區",
      "publish_duration" : "2014-05-23/2014-05-26",
      "publish_from" : "2014-05-23",
      "publish_until" : "2014-05-26",
      "telephone" : "07-7424163"
   },
   {
      "area" : "【區域1】台中市和平區梨山、松茂等地。",
      "interval_from" : "2014-05-23T18:00+08",
      "interval_until" : "2014-05-26T18:00+08",
      "publish_area" : "424台中市和平區",
      "publish_duration" : "2014-05-23/2014-05-27",
      "publish_from" : "2014-05-23",
      "publish_until" : "2014-05-27",
      "telephone" : ""
   },
   {
      "area" : "【區域1】高雄市鳳山區鳳山區北平路附近(北側)",
      "interval_from" : "2014-05-26T13:00+08",
      "interval_until" : "2014-05-26T17:00+08",
      "publish_area" : "830高雄市鳳山區",
      "publish_duration" : "2014-05-23/2014-05-27",
      "publish_from" : "2014-05-23",
      "publish_until" : "2014-05-27",
      "telephone" : "07-7424163"
   },
   {
      "area" : "【區域1】高雄市鳥松區鳥松區美山路36巷附近",
      "interval_from" : "2014-05-26T08:00+08",
      "interval_until" : "2014-05-26T12:00+08",
      "publish_area" : "833高雄市鳥松區",
      "publish_duration" : "2014-05-23/2014-05-27",
      "publish_from" : "2014-05-23",
      "publish_until" : "2014-05-27",
      "telephone" : "07-7424163"
   },
   {
      "area" : "【區域1】彰化縣田尾鄉力行巷;四維巷;饒平村;建平路一段",
      "interval_comment" : "8時至下午5時",
      "interval_from" : "2014-05-23T12:00+08",
      "interval_until" : "2014-05-29T17:00+08",
      "publish_area" : "522彰化縣田尾鄉",
      "publish_duration" : "2014-05-23/2014-05-30",
      "publish_from" : "2014-05-23",
      "publish_until" : "2014-05-30",
      "telephone" : "04-8882073    0912-975533"
   },
   {
      "area" : "【區域1】宜蘭縣五結鄉利興一路;利興二路;利興三路;利工三路;利工一路二段;利工二路;利工三路二段;利成路一段;新店路;季水路;成鳳路;利寶路;親河路一段;季水北巷;濱海路;錦草路;濱海路;成興路;宜蘭縣蘇澳鎮濱海路一段;濱海路二段;區界東路;區界西路",
      "interval_from" : "2014-05-27T13:00+08",
      "interval_until" : "2014-05-27T17:00+08",
      "publish_area" : "268宜蘭縣五結鄉     270宜蘭縣蘇澳鎮",
      "publish_duration" : "2014-05-23/2014-05-28",
      "publish_from" : "2014-05-23",
      "publish_until" : "2014-05-28",
      "telephone" : "0919934411"
   },
   {
      "area" : "【區域1】宜蘭縣五結鄉利興一路;利興二路;利興三路;利工三路;利工一路二段;利工二路;利工三路二段;利成路一段;新店路;季水路;成鳳路;利寶路;親河路一段;季水北巷;濱海路;錦草路;濱海路;成興路;宜蘭縣蘇澳鎮濱海路一段;濱海路二段;區界東路;區界西路",
      "interval_from" : "2014-05-27T13:00+08",
      "interval_until" : "2014-05-27T17:00+08",
      "publish_area" : "268宜蘭縣五結鄉     270宜蘭縣蘇澳鎮",
      "publish_duration" : "2014-05-23/2014-05-28",
      "publish_from" : "2014-05-23",
      "publish_until" : "2014-05-28",
      "telephone" : "0919934411"
   },
   {
      "area" : "【區域1】宜蘭縣五結鄉利興一路;利興二路;利興三路;利工三路;利工一路二段;利工二路;利工三路二段;利成路一段;新店路;季水路;成鳳路;利寶路;親河路一段;季水北巷;濱海路;成興路;宜蘭縣蘇澳鎮濱海路一段;濱海路二段;區界東路;區界西路",
      "interval_from" : "2014-05-27T13:00+08",
      "interval_until" : "2014-05-27T17:00+08",
      "publish_area" : "268宜蘭縣五結鄉     270宜蘭縣蘇澳鎮",
      "publish_duration" : "2014-05-23/2014-05-28",
      "publish_from" : "2014-05-23",
      "publish_until" : "2014-05-28",
      "telephone" : "0919934411"
   },
   {
      "area" : "【區域1】嘉義市西區後驛里竹文街97巷、後驛街69巷、75巷等所有住戶",
      "interval_from" : "2014-05-26T08:00+08",
      "interval_until" : "2014-05-26T18:00+08",
      "publish_area" : "600嘉義市西區",
      "publish_duration" : "2014-05-23/2014-05-27",
      "publish_from" : "2014-05-23",
      "publish_until" : "2014-05-27",
      "telephone" : "05-2252670轉252"
   },
   {
      "area" : "【區域1】彰化縣彰化市茄苳路二段;寶部路",
      "interval_comment" : "每日上午8點至下午6點",
      "interval_from" : "2014-05-23T14:00+08",
      "interval_until" : "2014-05-30T17:30+08",
      "publish_area" : "500彰化縣彰化市",
      "publish_duration" : "2014-05-23/2014-05-31",
      "publish_from" : "2014-05-23",
      "publish_until" : "2014-05-31",
      "telephone" : "04-7353883"
   },
   {
      "area" : "【區域1】新北市林口區粉寮路一段、醒吾新村",
      "interval_from" : "2014-05-24T08:00+08",
      "interval_until" : "2014-05-30T18:00+08",
      "publish_area" : "244新北市林口區",
      "publish_duration" : "2014-05-23/2014-05-31",
      "publish_from" : "2014-05-23",
      "publish_until" : "2014-05-31",
      "telephone" : "1910;02-26031880"
   },
   {
      "area" : "【區域1】台中市和平區梨山、松茂等地。",
      "interval_from" : "2014-05-23T18:00+08",
      "interval_until" : "2014-05-26T18:00+08",
      "publish_area" : "424台中市和平區",
      "publish_duration" : "2014-05-23/2014-05-27",
      "publish_from" : "2014-05-23",
      "publish_until" : "2014-05-27",
      "telephone" : ""
   },
   {
      "area" : "【區域1】雲林縣四湖鄉崙南村;中山路",
      "interval_comment" : "上午9時00分至下午18時00分",
      "interval_from" : "2014-05-24T09:00+08",
      "interval_until" : "2014-05-30T18:00+08",
      "publish_area" : "654雲林縣四湖鄉",
      "publish_duration" : "2014-05-23/2014-05-31",
      "publish_from" : "2014-05-23",
      "publish_until" : "2014-05-31",
      "telephone" : "05-6982250"
   },
   {
      "area" : "【區域1】花蓮縣花蓮市國安里;國威里;大同街;中山路;明禮路;林森路;建國路;復興新村;復興街;明心街;三民街",
      "interval_comment" : "每日下午13點至下午17點",
      "interval_from" : "2014-05-24T13:00+08",
      "interval_until" : "2014-05-25T17:00+08",
      "publish_area" : "970花蓮縣花蓮市",
      "publish_duration" : "2014-05-23/2014-05-26",
      "publish_from" : "2014-05-23",
      "publish_until" : "2014-05-26",
      "telephone" : "03-8325304"
   },
   {
      "area" : "【區域1】台中市南區忠孝路57巷以東.國光路134巷以南.國光路以西.忠孝路以北",
      "interval_from" : "2014-06-04T08:30+08",
      "interval_until" : "2014-06-04T17:30+08",
      "publish_area" : "402台中市南區",
      "publish_duration" : "2014-05-23/2014-06-05",
      "publish_from" : "2014-05-23",
      "publish_until" : "2014-06-05",
      "telephone" : "04-22210169"
   },
   {
      "area" : "【區域1】台中市西屯區臺灣大道4段671巷以東.臺灣大道4段以南.安和路以西.安和三街以北",
      "interval_from" : "2014-06-09T08:30+08",
      "interval_until" : "2014-06-09T17:30+08",
      "publish_area" : "407台中市西屯區",
      "publish_duration" : "2014-05-23/2014-06-10",
      "publish_from" : "2014-05-23",
      "publish_until" : "2014-06-10",
      "telephone" : "04-22210169"
   },
   {
      "area" : "【區域1】台中市南屯區大聖街以東.大墩十二街以南.大昌街以西.大墩十一街以北",
      "interval_from" : "2014-06-11T08:30+08",
      "interval_until" : "2014-06-11T17:30+08",
      "publish_area" : "408台中市南屯區",
      "publish_duration" : "2014-05-23/2014-06-12",
      "publish_from" : "2014-05-23",
      "publish_until" : "2014-06-12",
      "telephone" : "04-22210169"
   },
   {
      "area" : "【區域1】台中市西屯區安和路以東.福泰東路以南.福裕路以西.福科路以北",
      "interval_from" : "2014-06-13T08:30+08",
      "interval_until" : "2014-06-13T17:30+08",
      "publish_area" : "407台中市西屯區",
      "publish_duration" : "2014-05-23/2014-06-14",
      "publish_from" : "2014-05-23",
      "publish_until" : "2014-06-14",
      "telephone" : "04-22210169"
   },
   {
      "area" : "【區域1】台中市南區文心南路901巷以東.文心南路以南.文心南路以西.福田二街以北",
      "interval_from" : "2014-06-13T08:30+08",
      "interval_until" : "2014-06-13T17:30+08",
      "publish_area" : "402台中市南區",
      "publish_duration" : "2014-05-23/2014-06-14",
      "publish_from" : "2014-05-23",
      "publish_until" : "2014-06-14",
      "telephone" : "04-22210169"
   },
   {
      "area" : "【區域1】台中市南屯區楓樹西街以東.楓樹西街366巷以南.永春東三路以西.永春東三路110巷以北",
      "interval_from" : "2014-06-17T08:30+08",
      "interval_until" : "2014-06-17T17:30+08",
      "publish_area" : "408台中市南屯區",
      "publish_duration" : "2014-05-23/2014-06-18",
      "publish_from" : "2014-05-23",
      "publish_until" : "2014-06-18",
      "telephone" : "04-22210169"
   },
   {
      "area" : "【區域1】台中市南屯區龍富路4段以東.五權西路2段以南.益豐路4段以西.龍富十八路以北",
      "interval_from" : "2014-06-19T08:30+08",
      "interval_until" : "2014-06-19T17:30+08",
      "publish_area" : "408台中市南屯區",
      "publish_duration" : "2014-05-23/2014-06-20",
      "publish_from" : "2014-05-23",
      "publish_until" : "2014-06-20",
      "telephone" : "04-22210169"
   },
   {
      "area" : "【區域1】台中市西區大忠南街以東.五權西路一段以南.忠明南路以西.南屯路二段以北",
      "interval_from" : "2014-05-26T08:30+08",
      "interval_until" : "2014-05-26T16:00+08",
      "publish_area" : "403台中市西區",
      "publish_duration" : "2014-05-23/2014-05-27",
      "publish_from" : "2014-05-23",
      "publish_until" : "2014-05-27",
      "telephone" : "04-22210169"
   },
   {
      "area" : "【區域1】新北市三峽區國際一街、國際二街、國學街",
      "interval_comment" : "每日上午9時至下午5時",
      "interval_from" : "2014-05-24T09:00+08",
      "interval_until" : "2014-05-25T17:00+08",
      "publish_area" : "237新北市三峽區",
      "publish_duration" : "2014-05-23/2014-05-26",
      "publish_from" : "2014-05-23",
      "publish_until" : "2014-05-26",
      "telephone" : "26792224 26792527"
   },
   {
      "area" : "【區域1】宜蘭縣冬山鄉永安路",
      "interval_from" : "2014-05-26T13:00+08",
      "interval_until" : "2014-05-26T17:00+08",
      "publish_area" : "269宜蘭縣冬山鄉",
      "publish_duration" : "2014-05-23/2014-05-27",
      "publish_from" : "2014-05-23",
      "publish_until" : "2014-05-27",
      "telephone" : "039510028 ; 0932087863"
   },
   {
      "area" : "【區域1】新北市林口區東明一街;東明二街;東明三街;興林一街;興林路",
      "interval_comment" : "每日上午9點30分至下午4點30分",
      "interval_from" : "2014-05-26T09:30+08",
      "interval_until" : "2014-05-26T16:30+08",
      "publish_area" : "244新北市林口區",
      "publish_duration" : "2014-05-23/2014-05-27",
      "publish_from" : "2014-05-23",
      "publish_until" : "2014-05-27",
      "telephone" : "02-26031880"
   },
   {
      "area" : "【區域1】雲林縣土庫鎮順天里;奮起里;興新里;下店;中央路;秀潭;新興",
      "interval_comment" : "每日上午8點至下午6點",
      "interval_from" : "2014-05-19T08:30+08",
      "interval_until" : "2014-05-25T18:00+08",
      "publish_area" : "633雲林縣土庫鎮",
      "publish_duration" : "2014-05-24/2014-05-26",
      "publish_from" : "2014-05-24",
      "publish_until" : "2014-05-26",
      "telephone" : "05-6625545"
   },
   {
      "area" : "【區域3】台南市永康區中山南路(544巷、568巷、616巷)、忠孝路、復國一路、永二街、國華街、復華八街、復華十街、復華七街",
      "interval_comment" : "每日上午8:30至下午17:30",
      "interval_from" : "2014-5-22T08:30+08",
      "interval_until" : "2014-5-28T17:30+08",
      "publish_area" : "710台南市永康區",
      "publish_duration" : "2014-05-24/2014-05-29",
      "publish_from" : "2014-05-24",
      "publish_until" : "2014-05-29",
      "telephone" : "1910    06-2325714"
   },
   {
      "area" : "【區域1】台南市永康區中山南路546號~686號(含544巷、568巷、644巷662巷)、忠孝路250號~485號(含巷弄)",
      "interval_comment" : "每日上午8:30至下午17:30",
      "interval_from" : "2014-05-22T08:30+08",
      "interval_until" : "2014-05-28T17:30+08",
      "publish_area" : "710台南市永康區",
      "publish_duration" : "2014-05-24/2014-05-29",
      "publish_from" : "2014-05-24",
      "publish_until" : "2014-05-29",
      "telephone" : "1910    06-2325714"
   },
   {
      "area" : "【區域1】宜蘭縣蘇澳鎮蘇澳鎮永榮里永愛路160號~246號",
      "interval_from" : "2014-05-26T13:00+08",
      "interval_until" : "2014-05-26T16:00+08",
      "publish_area" : "270宜蘭縣蘇澳鎮",
      "publish_duration" : "2014-05-24/2014-05-27",
      "publish_from" : "2014-05-24",
      "publish_until" : "2014-05-27",
      "telephone" : "03-9589176"
   },
   {
      "area" : "【區域1】台中市清水區星河路500~700號",
      "interval_from" : "2014-05-25T09:00+08",
      "interval_until" : "2014-05-25T13:00+08",
      "publish_area" : "436台中市清水區",
      "publish_duration" : "2014-05-25/2014-05-26",
      "publish_from" : "2014-05-25",
      "publish_until" : "2014-05-26",
      "telephone" : ""
   },
   {
      "area" : "【區域1】雲林縣斗六市中華路;三民路中正路等沿線用戶",
      "interval_from" : "2014-05-25T09:15+08",
      "interval_until" : "2014-05-25T12:30+08",
      "publish_area" : "640雲林縣斗六市",
      "publish_duration" : "2014-05-25/2014-05-26",
      "publish_from" : "2014-05-25",
      "publish_until" : "2014-05-26",
      "telephone" : "05-5322362"
   },
   {
      "area" : "【區域1】桃園縣觀音鄉工業五路;工業四路;國建一路;經建一路;經建二路;經建三路;經建四路;成功路二段;成功路三段",
      "interval_from" : "2014-05-25T10:00+08",
      "interval_until" : "2014-05-25T17:00+08",
      "publish_area" : "328桃園縣觀音鄉",
      "publish_duration" : "2014-05-25/2014-05-26",
      "publish_from" : "2014-05-25",
      "publish_until" : "2014-05-26",
      "telephone" : "3862156"
   },
   {
      "area" : "【區域1】台中市西屯區文華路.福星路.福上巷.慶合街.逢甲巷.永興巷.等附近一帶",
      "interval_from" : "2014-05-25T09:45+08",
      "interval_until" : "2014-05-25T16:45+08",
      "publish_area" : "407台中市西屯區",
      "publish_duration" : "2014-05-25/2014-05-26",
      "publish_from" : "2014-05-25",
      "publish_until" : "2014-05-26",
      "telephone" : "04-22442469.....1910"
   },
   {
      "area" : "【區域1】台東縣卑南鄉民生路",
      "interval_from" : "2014-05-25T10:00+08",
      "interval_until" : "2014-05-25T12:00+08",
      "publish_area" : "954台東縣卑南鄉",
      "publish_duration" : "2014-05-25/2014-05-26",
      "publish_from" : "2014-05-25",
      "publish_until" : "2014-05-26",
      "telephone" : ""
   },
   {
      "area" : "【區域1】桃園縣新屋鄉望間村",
      "interval_from" : "2014-05-25T07:36+08",
      "interval_until" : "2014-05-25T17:30+08",
      "publish_area" : "327桃園縣新屋鄉",
      "publish_duration" : "2014-05-25/2014-05-26",
      "publish_from" : "2014-05-25",
      "publish_until" : "2014-05-26",
      "telephone" : "03-4789261"
   },
   {
      "area" : "【區域1】高雄市大寮區鳳林二路(新厝路口到仁德路口)",
      "interval_comment" : "上午8點至下午6點",
      "interval_from" : "2014-05-26T09:00+08",
      "interval_until" : "2014-05-26T18:00+08",
      "publish_area" : "831高雄市大寮區",
      "publish_duration" : "2014-05-25/2014-05-27",
      "publish_from" : "2014-05-25",
      "publish_until" : "2014-05-27",
      "telephone" : "077883714"
   },
   {
      "area" : "【區域1】高雄市大寮區鳳林二路(新厝路口到仁德路口)",
      "interval_comment" : "上午8點至下午6點",
      "interval_from" : "2014-05-26T09:00+08",
      "interval_until" : "2014-05-26T18:00+08",
      "publish_area" : "831高雄市大寮區",
      "publish_duration" : "2014-05-25/2014-05-27",
      "publish_from" : "2014-05-25",
      "publish_until" : "2014-05-27",
      "telephone" : "077883714"
   },
   {
      "area" : "【區域1】苗栗縣苗栗市苗栗市維祥街全部",
      "interval_from" : "2014-05-25T13:00+08",
      "interval_until" : "2014-05-25T17:00+08",
      "publish_area" : "360苗栗縣苗栗市",
      "publish_duration" : "2014-05-25/2014-05-26",
      "publish_from" : "2014-05-25",
      "publish_until" : "2014-05-26",
      "telephone" : "0930-965060.320334"
   },
   {
      "area" : "【區域1】苗栗縣苗栗市苗栗市維祥街全部",
      "interval_from" : "2014-05-25T13:00+08",
      "interval_until" : "2014-05-25T17:00+08",
      "publish_area" : "360苗栗縣苗栗市",
      "publish_duration" : "2014-05-25/2014-05-26",
      "publish_from" : "2014-05-25",
      "publish_until" : "2014-05-26",
      "telephone" : "0930-965060.320334"
   },
   {
      "area" : "【區域1】新竹市北區成德一街;成德二街;成德路;崧嶺路;中山路",
      "interval_from" : "2014-05-25T11:30+08",
      "interval_until" : "2014-05-25T17:30+08",
      "publish_area" : "300新竹市北區",
      "publish_duration" : "2014-05-25/2014-05-26",
      "publish_from" : "2014-05-25",
      "publish_until" : "2014-05-26",
      "telephone" : "5733523"
   },
   {
      "area" : "【區域1】宜蘭縣三星鄉三星路四段",
      "interval_from" : "2014-05-25T13:00+08",
      "interval_until" : "2014-05-25T16:00+08",
      "publish_area" : "266宜蘭縣三星鄉",
      "publish_duration" : "2014-05-25/2014-05-26",
      "publish_from" : "2014-05-25",
      "publish_until" : "2014-05-26",
      "telephone" : "0937-849892"
   },
   {
      "area" : "【區域1】宜蘭縣三星鄉三星路四段",
      "interval_from" : "2014-05-25T13:00+08",
      "interval_until" : "2014-05-25T16:00+08",
      "publish_area" : "266宜蘭縣三星鄉",
      "publish_duration" : "2014-05-25/2014-05-26",
      "publish_from" : "2014-05-25",
      "publish_until" : "2014-05-26",
      "telephone" : "0937-849892（林挺枝）"
   },
   {
      "area" : "【區域1】宜蘭縣三星鄉三星路四段",
      "interval_from" : "2014-05-25T13:00+08",
      "interval_until" : "2014-05-25T16:00+08",
      "publish_area" : "266宜蘭縣三星鄉",
      "publish_duration" : "2014-05-25/2014-05-26",
      "publish_from" : "2014-05-25",
      "publish_until" : "2014-05-26",
      "telephone" : "0937-849892（林挺枝）"
   },
   {
      "area" : "【區域1】台南市龍崎區全部村里",
      "interval_from" : "2014-05-25T12:35+08",
      "interval_until" : "2014-05-25T17:00+08",
      "publish_area" : "719台南市龍崎區",
      "publish_duration" : "2014-05-25/2014-05-26",
      "publish_from" : "2014-05-25",
      "publish_until" : "2014-05-26",
      "telephone" : ""
   },
   {
      "area" : "【區域1】新北市林口區隆林街、東湖路、興林路、東明1~3街、育林街、仁愛路二段附近一帶",
      "interval_from" : "2014-05-25T14:50+08",
      "interval_until" : "2014-05-25T18:00+08",
      "publish_area" : "244新北市林口區",
      "publish_duration" : "2014-05-25/2014-05-26",
      "publish_from" : "2014-05-25",
      "publish_until" : "2014-05-26",
      "telephone" : ""
   },
   {
      "area" : "【區域1】嘉義縣民雄鄉大崎村全",
      "interval_from" : "2014-05-25T15:30+08",
      "interval_until" : "2014-05-25T18:00+08",
      "publish_area" : "621嘉義縣民雄鄉",
      "publish_duration" : "2014-05-25/2014-05-26",
      "publish_from" : "2014-05-25",
      "publish_until" : "2014-05-26",
      "telephone" : ""
   },
   {
      "area" : "【區域1】台中市北區健行路.博館路.太原路.中港路.西屯路等附近一帶",
      "interval_from" : "2014-05-25T15:45+08",
      "interval_until" : "2014-05-25T22:45+08",
      "publish_area" : "404台中市北區",
      "publish_duration" : "2014-05-25/2014-05-26",
      "publish_from" : "2014-05-25",
      "publish_until" : "2014-05-26",
      "telephone" : "04-22442469"
   },
   {
      "area" : "【區域1】新竹市東區民主路、民族路、中央路、自由路、經國路1.2段附近一帶",
      "interval_from" : "2014-05-25T16:00+08",
      "interval_until" : "2014-05-25T19:00+08",
      "publish_area" : "300新竹市東區",
      "publish_duration" : "2014-05-25/2014-05-26",
      "publish_from" : "2014-05-25",
      "publish_until" : "2014-05-26",
      "telephone" : ""
   },
   {
      "area" : "【區域1】宜蘭縣蘇澳鎮永光路.延平路",
      "interval_from" : "2014-05-25T17:00+08",
      "interval_until" : "2014-05-25T20:00+08",
      "publish_area" : "270宜蘭縣蘇澳鎮",
      "publish_duration" : "2014-05-25/2014-05-26",
      "publish_from" : "2014-05-25",
      "publish_until" : "2014-05-26",
      "telephone" : ""
   },
   {
      "area" : "【區域1】台南市永康區中山南路546號~686號(含544巷、568巷、644巷662巷)、忠孝路250號~485號(含巷弄)",
      "interval_comment" : "每日上午8:30至下午17:30",
      "interval_from" : "2014-05-22T08:30+08",
      "interval_until" : "2014-05-28T20:30+08",
      "publish_area" : "710台南市永康區",
      "publish_duration" : "2014-05-25/2014-05-29",
      "publish_from" : "2014-05-25",
      "publish_until" : "2014-05-29",
      "telephone" : "1910    06-2325714"
   },
   {
      "area" : "【區域3】台南市永康區中山南路(544巷、568巷、616巷)、忠孝路、復國一路、永二街、國華街、復華八街、復華十街、復華七街",
      "interval_comment" : "每日上午8:30至下午17:30",
      "interval_from" : "2014-5-22T08:30+08",
      "interval_until" : "2014-5-28T17:30+08",
      "publish_area" : "710台南市永康區",
      "publish_duration" : "2014-05-25/2014-05-29",
      "publish_from" : "2014-05-25",
      "publish_until" : "2014-05-29",
      "telephone" : "1910    06-2325714"
   },
   {
      "area" : "【區域1】新竹縣寶山鄉雙溪村;明湖一街;明湖二街;明湖三街;明湖五街;明湖路;寶山五街;寶山路一段;寶山路二段;",
      "interval_from" : "2014-05-25T19:20+08",
      "interval_until" : "2014-05-26T01:20+08",
      "publish_area" : "308新竹縣寶山鄉",
      "publish_duration" : "2014-05-25/2014-05-27",
      "publish_from" : "2014-05-25",
      "publish_until" : "2014-05-27",
      "telephone" : "5733523"
   },
   {
      "area" : "【區域3】新竹縣寶山鄉雙溪村;明湖一街;明湖二街;明湖三街;明湖五街;明湖路;寶山五街;寶山路一段;寶山路二段;",
      "interval_from" : "2014-05-25T19:20+08",
      "interval_until" : "2014-05-26T01:20+08",
      "publish_area" : "308新竹縣寶山鄉",
      "publish_duration" : "2014-05-25/2014-05-27",
      "publish_from" : "2014-05-25",
      "publish_until" : "2014-05-27",
      "telephone" : "5733523"
   },
   {
      "area" : "【區域1】宜蘭縣礁溪鄉瑪璘路40號、41號、42號、43號、44號",
      "interval_from" : "2014-05-25T19:40+08",
      "interval_until" : "2014-05-26T09:00+08",
      "publish_area" : "262宜蘭縣礁溪鄉",
      "publish_duration" : "2014-05-25/2014-05-27",
      "publish_from" : "2014-05-25",
      "publish_until" : "2014-05-27",
      "telephone" : ""
   },
   {
      "area" : "【區域1】台南市永康區中山南路546號~686號(含544巷、568巷、644巷662巷)、忠孝路250號~485號(含巷弄)",
      "interval_comment" : "每日上午8:30至下午17:30",
      "interval_from" : "2014-05-22T08:30+08",
      "interval_until" : "2014-05-28T17:30+08",
      "publish_area" : "710台南市永康區",
      "publish_duration" : "2014-05-25/2014-05-29",
      "publish_from" : "2014-05-25",
      "publish_until" : "2014-05-29",
      "telephone" : "1910    06-2325714"
   },
   {
      "area" : "【區域3】台南市永康區中山南路(544巷、568巷、616巷)、忠孝路、復國一路、永二街、國華街、復華八街、復華十街、復華七街",
      "interval_comment" : "每日上午8:30至下午17:30",
      "interval_from" : "2014-5-22T08:30+08",
      "interval_until" : "2014-5-28T17:30+08",
      "publish_area" : "710台南市永康區",
      "publish_duration" : "2014-05-25/2014-05-29",
      "publish_from" : "2014-05-25",
      "publish_until" : "2014-05-29",
      "telephone" : "1910    06-2325714"
   },
   {
      "area" : "【區域1】花蓮縣花蓮市東興一街、二街、民孝街",
      "interval_from" : "2014-05-25T17:00+08",
      "interval_until" : "2014-05-25T22:00+08",
      "publish_area" : "970花蓮縣花蓮市",
      "publish_duration" : "2014-05-25/2014-05-26",
      "publish_from" : "2014-05-25",
      "publish_until" : "2014-05-26",
      "telephone" : ""
   },
   {
      "area" : "【區域1】台南市新營區洪厝寮",
      "interval_from" : "2014-05-25T22:00+08",
      "interval_until" : "2014-05-26T02:00+08",
      "publish_area" : "730台南市新營區",
      "publish_duration" : "2014-05-25/2014-05-27",
      "publish_from" : "2014-05-25",
      "publish_until" : "2014-05-27",
      "telephone" : ""
   },
   {
      "area" : "【區域1】苗栗縣三義鄉雙潭村;苗栗縣銅鑼鄉盛隆村;新隆村;興隆村",
      "interval_from" : "2014-05-25T22:20+08",
      "interval_until" : "2014-05-26T18:00+08",
      "publish_area" : "367苗栗縣三義鄉     366苗栗縣銅鑼鄉",
      "publish_duration" : "2014-05-25/2014-05-27",
      "publish_from" : "2014-05-25",
      "publish_until" : "2014-05-27",
      "telephone" : "037-986206  037-986218"
   },
   {
      "area" : "【區域1】台南市安南區慶和路1段",
      "interval_from" : "2014-05-26T08:00+08",
      "interval_until" : "2014-05-26T18:00+08",
      "publish_area" : "709台南市安南區",
      "publish_duration" : "2014-05-26/2014-05-27",
      "publish_from" : "2014-05-26",
      "publish_until" : "2014-05-27",
      "telephone" : "06-3036097"
   },
   {
      "area" : "【區域1】新北市板橋區篤行路一段雙號側含巷弄",
      "interval_from" : "2014-05-26T07:00+08",
      "interval_until" : "2014-05-26T11:00+08",
      "publish_area" : "220新北市板橋區",
      "publish_duration" : "2014-05-26/2014-05-27",
      "publish_from" : "2014-05-26",
      "publish_until" : "2014-05-27",
      "telephone" : "02-26812254"
   },
   {
      "area" : "【區域1】嘉義市東區嘉義市(太平里)新生路523號至667-2號等巷弄，新生路540號至630號等巷弄，維新路216巷，博東路200巷。",
      "interval_comment" : "每日上午8點至下午6點",
      "interval_from" : "2014-05-29T08:00+08",
      "interval_until" : "2014-05-30T18:00+08",
      "publish_area" : "600嘉義市東區",
      "publish_duration" : "2014-05-26/2014-05-31",
      "publish_from" : "2014-05-26",
      "publish_until" : "2014-05-31",
      "telephone" : "2252670*310"
   },
   {
      "area" : "【區域1】嘉義市西區嘉義市(福民里)福州七街95-101號，世賢路三段175-387號，南京路295-319號。",
      "interval_comment" : "每日上午8點至下午6點",
      "interval_from" : "2014-05-28T08:00+08",
      "interval_until" : "2014-05-28T18:00+08",
      "publish_area" : "600嘉義市西區",
      "publish_duration" : "2014-05-26/2014-05-29",
      "publish_from" : "2014-05-26",
      "publish_until" : "2014-05-29",
      "telephone" : "2252670*310"
   },
   {
      "area" : "【區域1】雲林縣土庫鎮後埔里;後埔里外環路以北用戶及聖公母廟",
      "interval_from" : "2014-05-26T08:30+08",
      "interval_until" : "2014-05-26T17:30+08",
      "publish_area" : "633雲林縣土庫鎮",
      "publish_duration" : "2014-05-26/2014-05-27",
      "publish_from" : "2014-05-26",
      "publish_until" : "2014-05-27",
      "telephone" : "05-6625545  范雅聞0911155483"
   },
   {
      "area" : "【區域1】雲林縣元長鄉全部減壓供水;雲林縣北港鎮全部減壓供水",
      "interval_from" : "2014-05-26T08:00+08",
      "interval_until" : "2014-05-26T17:00+08",
      "publish_area" : "655雲林縣元長鄉     651雲林縣北港鎮",
      "publish_duration" : "2014-05-26/2014-05-27",
      "publish_from" : "2014-05-26",
      "publish_until" : "2014-05-27",
      "telephone" : "7832040"
   },
   {
      "area" : "【區域1】雲林縣水林鄉全部瞬間減壓供水;雲林縣北港鎮全部瞬間減壓供水",
      "interval_from" : "2014-05-26T13:00+08",
      "interval_until" : "2014-05-26T17:00+08",
      "publish_area" : "652雲林縣水林鄉     651雲林縣北港鎮",
      "publish_duration" : "2014-05-26/2014-05-27",
      "publish_from" : "2014-05-26",
      "publish_until" : "2014-05-27",
      "telephone" : "7832040"
   },
   {
      "area" : "【區域1】台東縣關山鎮新福里",
      "interval_comment" : "2014/05/26 早上9點至下午5點30分",
      "interval_from" : "2014-05-26T09:00+08",
      "interval_until" : "2014-05-26T17:30+08",
      "publish_area" : "956台東縣關山鎮",
      "publish_duration" : "2014-05-26/2014-05-27",
      "publish_from" : "2014-05-26",
      "publish_until" : "2014-05-27",
      "telephone" : "089-862625"
   },
   {
      "area" : "【區域1】屏東縣新園鄉五房村",
      "interval_from" : "2014-05-26T09:00+08",
      "interval_until" : "2014-05-26T12:00+08",
      "publish_area" : "932屏東縣新園鄉",
      "publish_duration" : "2014-05-26/2014-05-27",
      "publish_from" : "2014-05-26",
      "publish_until" : "2014-05-27",
      "telephone" : "08-8325550"
   },
   {
      "area" : "【區域1】屏東縣新園鄉五房村",
      "interval_from" : "2014-05-26T09:00+08",
      "interval_until" : "2014-05-26T12:00+08",
      "publish_area" : "932屏東縣新園鄉",
      "publish_duration" : "2014-05-26/2014-05-27",
      "publish_from" : "2014-05-26",
      "publish_until" : "2014-05-27",
      "telephone" : "08-8325550"
   },
   {
      "area" : "【區域1】新北市樹林區光興街全部",
      "interval_from" : "2014-05-26T09:30+08",
      "interval_until" : "2014-05-26T11:30+08",
      "publish_area" : "238新北市樹林區",
      "publish_duration" : "2014-05-26/2014-05-27",
      "publish_from" : "2014-05-26",
      "publish_until" : "2014-05-27",
      "telephone" : "02-26812254"
   },
   {
      "area" : "【區域1】台中市沙鹿區星河路500號至700號",
      "interval_from" : "2014-05-26T09:00+08",
      "interval_until" : "2014-05-26T13:00+08",
      "publish_area" : "433台中市沙鹿區",
      "publish_duration" : "2014-05-26/2014-05-27",
      "publish_from" : "2014-05-26",
      "publish_until" : "2014-05-27",
      "telephone" : "04-26222614"
   },
   {
      "area" : "【區域1】桃園縣楊梅市和平路全部",
      "interval_from" : "2014-05-26T09:00+08",
      "interval_until" : "2014-05-26T14:00+08",
      "publish_area" : "326桃園縣楊梅市",
      "publish_duration" : "2014-05-26/2014-05-27",
      "publish_from" : "2014-05-26",
      "publish_until" : "2014-05-27",
      "telephone" : "4789261"
   },
   {
      "area" : "【區域1】新北市樹林區長壽街19巷全部、復興路46~108號、啟智街25、25-1號",
      "interval_from" : "2014-05-27T09:00+08",
      "interval_until" : "2014-05-27T18:00+08",
      "publish_area" : "238新北市樹林區",
      "publish_duration" : "2014-05-26/2014-05-28",
      "publish_from" : "2014-05-26",
      "publish_until" : "2014-05-28",
      "telephone" : "02-26812254"
   },
   {
      "area" : "【區域1】新北市樹林區復興路102~130號",
      "interval_from" : "2014-05-28T09:00+08",
      "interval_until" : "2014-05-28T18:00+08",
      "publish_area" : "238新北市樹林區",
      "publish_duration" : "2014-05-26/2014-05-29",
      "publish_from" : "2014-05-26",
      "publish_until" : "2014-05-29",
      "telephone" : "02-26812254"
   },
   {
      "area" : "【區域1】彰化縣大村鄉山腳路一帶;彰化縣花壇鄉彰員路一段",
      "interval_comment" : "每日上午8點至下午6點",
      "interval_from" : "2014-05-26T08:00+08",
      "interval_until" : "2014-06-09T18:00+08",
      "publish_area" : "515彰化縣大村鄉     503彰化縣花壇鄉",
      "publish_duration" : "2014-05-26/2014-06-10",
      "publish_from" : "2014-05-26",
      "publish_until" : "2014-06-10",
      "telephone" : "04-7245031*308(監工人員吳宏麟)"
   },
   {
      "area" : "【區域1】彰化縣員林鎮南平街一帶",
      "interval_comment" : "每日上午8點至下午6點",
      "interval_from" : "2014-05-26T08:00+08",
      "interval_until" : "2014-06-09T18:00+08",
      "publish_area" : "510彰化縣員林鎮",
      "publish_duration" : "2014-05-26/2014-06-10",
      "publish_from" : "2014-05-26",
      "publish_until" : "2014-06-10",
      "telephone" : "04-7245031*302(監工人員梁福智)"
   },
   {
      "area" : "【區域1】彰化縣埤頭鄉十號路、(十號路500巷、499巷、473巷、445巷、511巷)、彰新路、埤頭路、斗苑東路王厝巷、埔尾路、七號路、斗苑東路424巷",
      "interval_comment" : "每日上午8點至下午6點",
      "interval_from" : "2014-05-26T08:00+08",
      "interval_until" : "2014-06-09T18:00+08",
      "publish_area" : "523彰化縣埤頭鄉",
      "publish_duration" : "2014-05-26/2014-06-10",
      "publish_from" : "2014-05-26",
      "publish_until" : "2014-06-10",
      "telephone" : "04-7245031*309"
   },
   {
      "area" : "【區域1】高雄市三民區水壓降低區域-中華路.建國三路.中山一路.三德西街.",
      "interval_from" : "2014-05-26T10:00+08",
      "interval_until" : "2014-05-26T18:00+08",
      "publish_area" : "807高雄市三民區",
      "publish_duration" : "2014-05-26/2014-05-27",
      "publish_from" : "2014-05-26",
      "publish_until" : "2014-05-27",
      "telephone" : "7311111-257"
   },
   {
      "area" : "【區域1】高雄市三民區水壓降低區域-建國二路.中山一路.忠孝路.長明街.",
      "interval_from" : "2014-05-26T12:00+08",
      "interval_until" : "2014-05-26T18:00+08",
      "publish_area" : "807高雄市三民區",
      "publish_duration" : "2014-05-26/2014-05-27",
      "publish_from" : "2014-05-26",
      "publish_until" : "2014-05-27",
      "telephone" : "7311111-257"
   },
   {
      "area" : "【區域1】彰化縣二林鎮太平路一帶",
      "interval_comment" : "每日上午8點至下午6點",
      "interval_from" : "2014-05-26T08:00+08",
      "interval_until" : "2014-06-09T18:00+08",
      "publish_area" : "526彰化縣二林鎮",
      "publish_duration" : "2014-05-26/2014-06-10",
      "publish_from" : "2014-05-26",
      "publish_until" : "2014-06-10",
      "telephone" : "04-7245031*309"
   },
   {
      "area" : "【區域1】高雄市鼓山區鼓山三路51巷.鼓山三路.明德路.新疆路.",
      "interval_from" : "2014-05-26T09:30+08",
      "interval_until" : "2014-05-26T17:30+08",
      "publish_area" : "804高雄市鼓山區",
      "publish_duration" : "2014-05-26/2014-05-27",
      "publish_from" : "2014-05-26",
      "publish_until" : "2014-05-27",
      "telephone" : "7311111-257"
   },
   {
      "area" : "【區域1】台中市霧峰區四德路(神農大帝廟至275巷口)雙號停水.沿路含巷弄",
      "interval_from" : "2014-05-26T09:00+08",
      "interval_until" : "2014-05-26T12:00+08",
      "publish_area" : "413台中市霧峰區",
      "publish_duration" : "2014-05-26/2014-05-27",
      "publish_from" : "2014-05-26",
      "publish_until" : "2014-05-27",
      "telephone" : "04-23393138"
   },
   {
      "area" : "【區域1】高雄市美濃區祿興、合和、中壇、福安、泰安、中圳、瀰濃、德興、清水及東門等10里皆受影響。",
      "interval_from" : "2014-05-27T08:00+08",
      "interval_until" : "2014-05-27T20:30+08",
      "publish_area" : "843高雄市美濃區",
      "publish_duration" : "2014-05-26/2014-05-28",
      "publish_from" : "2014-05-26",
      "publish_until" : "2014-05-28",
      "telephone" : "0928741027"
   },
   {
      "area" : "【區域1】台中市東區建中街(全部)，大公街(全部)，建成路(全部)，立德街(全部)，建德街(全部)，台中路(全部)，仁和路(全部)，立德東街(全部)等附近一帶",
      "interval_from" : "2014-05-26T09:18+08",
      "interval_until" : "2014-05-26T13:18+08",
      "publish_area" : "401台中市東區",
      "publish_duration" : "2014-05-26/2014-05-27",
      "publish_from" : "2014-05-26",
      "publish_until" : "2014-05-27",
      "telephone" : "22442469、1910"
   },
   {
      "area" : "【區域1】台中市烏日區五光路805巷一帶",
      "interval_from" : "2014-05-26T09:20+08",
      "interval_until" : "2014-05-26T10:30+08",
      "publish_area" : "414台中市烏日區",
      "publish_duration" : "2014-05-26/2014-05-27",
      "publish_from" : "2014-05-26",
      "publish_until" : "2014-05-27",
      "telephone" : "04-23381614"
   },
   {
      "area" : "【區域1】苗栗縣竹南鎮竹南里、照南里、正南里、新南里、營盤里、大厝里、聖福里、竹興里、山佳里、龍鳳里、中港里、中華里、中英里、中美里、開元里、海口里、天文里、港漧里、龍山里、大埔里、佳興里、崎頂里;苗栗縣頭份鎮田寮里",
      "interval_from" : "2014-05-29T08:00+08",
      "interval_until" : "2014-05-29T19:00+08",
      "publish_area" : "350苗栗縣竹南鎮     351苗栗縣頭份鎮",
      "publish_duration" : "2014-05-26/2014-05-30",
      "publish_from" : "2014-05-26",
      "publish_until" : "2014-05-30",
      "telephone" : "03-669621"
   },
   {
      "area" : "【區域1】高雄市橋頭區白樹里;橋頭里;成功北路一帶",
      "interval_comment" : "於5/26至5/31日每日上午9點至下午18點",
      "interval_from" : "2014-05-26T09:00+08",
      "interval_until" : "2014-05-31T18:00+08",
      "publish_area" : "825高雄市橋頭區",
      "publish_duration" : "2014-05-26/2014-06-01",
      "publish_from" : "2014-05-26",
      "publish_until" : "2014-06-01",
      "telephone" : "07-6222814"
   },
   {
      "area" : "【區域1】彰化縣大村鄉福興村;平和村;彰化縣花壇鄉永春村",
      "interval_from" : "2014-05-26T09:36+08",
      "interval_until" : "2014-05-26T17:30+08",
      "publish_area" : "515彰化縣大村鄉     503彰化縣花壇鄉",
      "publish_duration" : "2014-05-26/2014-05-27",
      "publish_from" : "2014-05-26",
      "publish_until" : "2014-05-27",
      "telephone" : "047867044"
   },
   {
      "area" : "【區域1】宜蘭縣礁溪鄉三皇路;大坡路;永興街;龍潭路",
      "interval_from" : "2014-05-26T09:40+08",
      "interval_until" : "2014-05-26T13:00+08",
      "publish_area" : "262宜蘭縣礁溪鄉",
      "publish_duration" : "2014-05-26/2014-05-27",
      "publish_from" : "2014-05-26",
      "publish_until" : "2014-05-27",
      "telephone" : "9233017"
   },
   {
      "area" : "【區域1】台東縣台東市豐樂里",
      "interval_from" : "2014-05-26T14:30+08",
      "interval_until" : "2014-05-26T16:30+08",
      "publish_area" : "950台東縣台東市",
      "publish_duration" : "2014-05-26/2014-05-27",
      "publish_from" : "2014-05-26",
      "publish_until" : "2014-05-27",
      "telephone" : "陳德昇 0939592535"
   },
   {
      "area" : "【區域1】新竹市東區中山路;新竹市香山區中山路",
      "interval_from" : "2014-05-26T09:30+08",
      "interval_until" : "2014-05-26T14:30+08",
      "publish_area" : "300新竹市東區       300新竹市香山區",
      "publish_duration" : "2014-05-26/2014-05-27",
      "publish_from" : "2014-05-26",
      "publish_until" : "2014-05-27",
      "telephone" : "1910.5733523"
   },
   {
      "area" : "【區域1】高雄市左營區新庄子路499巷15號附近一帶",
      "interval_from" : "2014-05-26T09:46+08",
      "interval_until" : "2014-05-26T14:00+08",
      "publish_area" : "813高雄市左營區",
      "publish_duration" : "2014-05-26/2014-05-27",
      "publish_from" : "2014-05-26",
      "publish_until" : "2014-05-27",
      "telephone" : "07-7321319"
   },
   {
      "area" : "【區域1】宜蘭縣蘇澳鎮志成路363巷內;聖賢路少部分(與志成路交界處)",
      "interval_from" : "2014-05-26T10:00+08",
      "interval_until" : "2014-05-26T13:00+08",
      "publish_area" : "270宜蘭縣蘇澳鎮",
      "publish_duration" : "2014-05-26/2014-05-27",
      "publish_from" : "2014-05-26",
      "publish_until" : "2014-05-27",
      "telephone" : "0937849892"
   },
   {
      "area" : "【區域1】屏東縣屏東市建國路311號以後之單號用戶",
      "interval_from" : "2014-05-26T10:00+08",
      "interval_until" : "2014-05-26T12:00+08",
      "publish_area" : "900屏東縣屏東市",
      "publish_duration" : "2014-05-26/2014-05-27",
      "publish_from" : "2014-05-26",
      "publish_until" : "2014-05-27",
      "telephone" : "08-7226170、7220040"
   },
   {
      "area" : "【區域1】高雄市小港區廈莊一街及附近一帶",
      "interval_from" : "2014-05-26T10:00+08",
      "interval_until" : "2014-05-26T11:30+08",
      "publish_area" : "812高雄市小港區",
      "publish_duration" : "2014-05-26/2014-05-27",
      "publish_from" : "2014-05-26",
      "publish_until" : "2014-05-27",
      "telephone" : "07-7321319"
   },
   {
      "area" : "【區域1】花蓮縣壽豐鄉鹽寮;橄樹腳",
      "interval_from" : "2014-05-26T10:15+08",
      "interval_until" : "2014-05-26T13:30+08",
      "publish_area" : "974花蓮縣壽豐鄉",
      "publish_duration" : "2014-05-26/2014-05-27",
      "publish_from" : "2014-05-26",
      "publish_until" : "2014-05-27",
      "telephone" : "038325304"
   },
   {
      "area" : "【區域1】宜蘭縣羅東鎮光榮路500巷",
      "interval_from" : "2014-05-26T13:00+08",
      "interval_until" : "2014-05-26T17:00+08",
      "publish_area" : "265宜蘭縣羅東鎮",
      "publish_duration" : "2014-05-26/2014-05-27",
      "publish_from" : "2014-05-26",
      "publish_until" : "2014-05-27",
      "telephone" : "0937849882"
   },
   {
      "area" : "【區域1】嘉義縣竹崎鄉龍山村;水尾仔;汪厝",
      "interval_from" : "2014-05-26T10:00+08",
      "interval_until" : "2014-05-26T15:00+08",
      "publish_area" : "604嘉義縣竹崎鄉",
      "publish_duration" : "2014-05-26/2014-05-27",
      "publish_from" : "2014-05-26",
      "publish_until" : "2014-05-27",
      "telephone" : "2611075"
   },
   {
      "area" : "【區域1】台南市鹽水區洪厝寮",
      "interval_from" : "2014-05-25T22:00+08",
      "interval_until" : "2014-05-26T02:00+08",
      "publish_area" : "737台南市鹽水區",
      "publish_duration" : "2014-05-26/2014-05-27",
      "publish_from" : "2014-05-26",
      "publish_until" : "2014-05-27",
      "telephone" : ""
   },
   {
      "area" : "【區域1】新北市三重區水壓降低-新北大道，光華路，頂崁街，興德路，重新路五段，光復路一.二段，中興北街，中興南街，五谷王北街，五谷王南街等用水戶(含單雙號側及周邊巷弄);里別：頂崁里，中興里，谷王里，五谷里，德厚里;新北市五股區水壓降低-五股區：五工路;五工一路~五工六路;五權路;五權一路~五權八路;中港南路 以上附近地區水壓低。;新北市新莊區水壓降低-中華路一.二.三段，中港路，中原路，中原東路，中央路，昌義路，昌平路，昌仁路，昌和街，昌明街，昌學街，昌隆街，昌盛街，昌智路，昌德街，榮華路一段，化成路，思源路，復興路二.三段，公園路，新央街，新中街，民樂街，福樂街，福壽街，長青街，自信街，自立街，自由街，自強街，自重街，自治街，明中街，明智街，銘德街，民生街，博愛路，幸福路，幸福東路，福美街，福前街，福德一街，福德二街，福德三街，頭成路，頭前路，頭興街，中正路等用水戶(含單雙號側及周邊巷弄)【三重區及新莊區的水壓降低區域包含中華路以東，疏洪西路以西，新北大道以南，環河路以北之區塊】;里別：福基里，頭前里，化成里，昌平里，中隆里，和平里，昌信里，昌明里，昌隆里，信義里，幸福里，仁義里，仁愛里，自信里，自強里，自立里，中華里，思源里，思賢里，中美里，恆安里，立人里，文明里，文德里",
      "interval_from" : "2014-05-27T10:00+08",
      "interval_until" : "2014-05-28T16:00+08",
      "publish_area" : "241新北市三重區     248新北市五股區     242新北市新莊區",
      "publish_duration" : "2014-05-26/2014-05-29",
      "publish_from" : "2014-05-26",
      "publish_until" : "2014-05-29",
      "telephone" : "客服中心：1910    區管理處：2996-8961    新莊服務所：2996-6681"
   },
   {
      "area" : "【區域3】新北市三重區新北大道，光華路，頂崁街，興德路，重新路五段，光復路一.二段，中興北街，中興南街，五谷王北街，五谷王南街等用水戶(含單雙號側及周邊巷弄);里別：頂崁里，中興里，谷王里，五谷里，德厚里;新北市五股區五股區：五工路;五工一路~五工六路;五權路;五權一路~五權八路;中港南路 以上附近地區水壓低。;新北市新莊區中華路一.二.三段，中港路，中原路，中原東路，中央路，昌義路，昌平路，昌仁路，昌和街，昌明街，昌學街，昌隆街，昌盛街，昌智路，昌德街，榮華路一段，化成路，思源路，復興路二.三段，公園路，新央街，新中街，民樂街，福樂街，福壽街，長青街，自信街，自立街，自由街，自強街，自重街，自治街，明中街，明智街，銘德街，民生街，博愛路，幸福路，幸福東路，福美街，福前街，福德一街，福德二街，福德三街，頭成路，頭前路，頭興街，中正路等用水戶(含單雙號側及周邊巷弄)【三重區及新莊區的水壓降低區域包含中華路以東，疏洪西路以西，新北大道以南，環河路以北之區塊】;里別：福基里，頭前里，化成里，昌平里，中隆里，和平里，昌信里，昌明里，昌隆里，信義里，幸福里，仁義里，仁愛里，自信里，自強里，自立里，中華里，思源里，思賢里，中美里，恆安里，立人里，文明里，文德里",
      "interval_from" : "2014-5-27T10:00+08",
      "interval_until" : "2014-5-28T16:00+08",
      "publish_area" : "241新北市三重區     248新北市五股區     242新北市新莊區",
      "publish_duration" : "2014-05-26/2014-05-29",
      "publish_from" : "2014-05-26",
      "publish_until" : "2014-05-29",
      "telephone" : "客服中心：1910    區管理處：2996-8961    新莊服務所：2996-6681"
   },
   {
      "area" : "【區域1】台東縣台東市西康路三段 青海路",
      "interval_from" : "2014-05-26T10:00+08",
      "interval_until" : "2014-05-26T18:00+08",
      "publish_area" : "950台東縣台東市",
      "publish_duration" : "2014-05-26/2014-05-27",
      "publish_from" : "2014-05-26",
      "publish_until" : "2014-05-27",
      "telephone" : "陳信志0928798357"
   },
   {
      "area" : "【區域1】台南市歸仁區田中里.龜洞里各部份.",
      "interval_from" : "2014-05-26T10:10+08",
      "interval_until" : "2014-05-26T12:10+08",
      "publish_area" : "711台南市歸仁區",
      "publish_duration" : "2014-05-26/2014-05-27",
      "publish_from" : "2014-05-26",
      "publish_until" : "2014-05-27",
      "telephone" : "06-2303756"
   },
   {
      "area" : "【區域1】花蓮縣花蓮市國威里;國安里;一心街;大同街;中山路;明心街;明禮路;林森路;建國路;復興街;進豐街;三民街",
      "interval_comment" : "下午13點至17點",
      "interval_from" : "2014-05-26T13:00+08",
      "interval_until" : "2014-05-26T17:00+08",
      "publish_area" : "970花蓮縣花蓮市",
      "publish_duration" : "2014-05-26/2014-05-27",
      "publish_from" : "2014-05-26",
      "publish_until" : "2014-05-27",
      "telephone" : "03-8325304"
   },
   {
      "area" : "【區域1】南投縣名間鄉炭寮村",
      "interval_from" : "2014-05-26T10:30+08",
      "interval_until" : "2014-05-26T15:00+08",
      "publish_area" : "551南投縣名間鄉",
      "publish_duration" : "2014-05-26/2014-05-27",
      "publish_from" : "2014-05-26",
      "publish_until" : "2014-05-27",
      "telephone" : "0492222635"
   },
   {
      "area" : "【區域1】台南市南區金華路一.二段、新興路、三官路、夏林路、仁慈街",
      "interval_from" : "2014-05-26T10:00+08",
      "interval_until" : "2014-05-26T18:00+08",
      "publish_area" : "702台南市南區",
      "publish_duration" : "2014-05-26/2014-05-27",
      "publish_from" : "2014-05-26",
      "publish_until" : "2014-05-27",
      "telephone" : "06-3036097"
   },
   {
      "area" : "【區域1】嘉義市東區林森東路、盧厝、精忠一村",
      "interval_from" : "2014-05-26T10:35+08",
      "interval_until" : "2014-05-26T12:00+08",
      "publish_area" : "600嘉義市東區",
      "publish_duration" : "2014-05-26/2014-05-27",
      "publish_from" : "2014-05-26",
      "publish_until" : "2014-05-27",
      "telephone" : "0978060560"
   },
   {
      "area" : "【區域1】新竹市東區建中一路;建中路;建功一路;建功二路;建功路.新源街.建新路.公道五路二段",
      "interval_from" : "2014-05-26T09:00+08",
      "interval_until" : "2014-05-26T23:00+08",
      "publish_area" : "300新竹市東區",
      "publish_duration" : "2014-05-26/2014-05-27",
      "publish_from" : "2014-05-26",
      "publish_until" : "2014-05-27",
      "telephone" : "1910.5733523"
   },
   {
      "area" : "【區域1】台南市安南區1.北安路3段 2.長溪路2段 3.頂安街 4.安豐一~六街  5.培安路、培安二街  6.安生街  7.總安路一段",
      "interval_comment" : "預計每日上午8點至下午18點 停水至18點以後恢復供水，遇雨順延",
      "interval_from" : "2014-05-20T08:00+08",
      "interval_until" : "2014-06-15T18:00+08",
      "publish_area" : "709台南市安南區",
      "publish_duration" : "2014-05-26/2014-06-16",
      "publish_from" : "2014-05-26",
      "publish_until" : "2014-06-16",
      "telephone" : "0932705794蔡先生"
   },
   {
      "area" : "【區域1】苗栗縣頭份鎮苗栗縣頭份鎮蘆竹里蘆竹路247號前漏水修理",
      "interval_from" : "2014-05-26T11:00+08",
      "interval_until" : "2014-05-26T13:00+08",
      "publish_area" : "351苗栗縣頭份鎮",
      "publish_duration" : "2014-05-26/2014-05-27",
      "publish_from" : "2014-05-26",
      "publish_until" : "2014-05-27",
      "telephone" : "〈037〉6253000.628000"
   },
   {
      "area" : "【區域1】高雄市新興區東海街70號前附近一帶",
      "interval_from" : "2014-05-26T10:43+08",
      "interval_until" : "2014-05-26T13:43+08",
      "publish_area" : "800高雄市新興區",
      "publish_duration" : "2014-05-26/2014-05-27",
      "publish_from" : "2014-05-26",
      "publish_until" : "2014-05-27",
      "telephone" : "07-7321319"
   },
   {
      "area" : "【區域1】新竹縣尖石鄉新樂村;義興村;嘉樂村",
      "interval_from" : "2014-05-26T10:30+08",
      "interval_until" : "2014-05-26T13:30+08",
      "publish_area" : "313新竹縣尖石鄉",
      "publish_duration" : "2014-05-26/2014-05-27",
      "publish_from" : "2014-05-26",
      "publish_until" : "2014-05-27",
      "telephone" : "1910 ; 035963356; 035963359"
   },
   {
      "area" : "【區域1】南投縣南投市內新里;內興里;光明里;光華里;光榮里;光輝里;東山里;軍功里;營北里;營南里等(水壓降低);南投縣草屯鎮山腳里;新厝里等(水壓降低)",
      "interval_from" : "2014-05-27T10:00+08",
      "interval_until" : "2014-05-27T21:00+08",
      "publish_area" : "540南投縣南投市     542南投縣草屯鎮",
      "publish_duration" : "2014-05-26/2014-05-28",
      "publish_from" : "2014-05-26",
      "publish_until" : "2014-05-28",
      "telephone" : "049-2563505.2566689"
   },
   {
      "area" : "【區域1】南投縣南投市文化南路",
      "interval_from" : "2014-05-26T11:00+08",
      "interval_until" : "2014-05-26T15:00+08",
      "publish_area" : "540南投縣南投市",
      "publish_duration" : "2014-05-26/2014-05-27",
      "publish_from" : "2014-05-26",
      "publish_until" : "2014-05-27",
      "telephone" : "0492222635"
   },
   {
      "area" : "【區域1】台中市沙鹿區北勢東路500~900號、北勢二街、鎮南路2段(含巷弄)、福幼街、北中一街(全含巷弄)",
      "interval_from" : "2014-05-26T11:00+08",
      "interval_until" : "2014-05-26T15:00+08",
      "publish_area" : "433台中市沙鹿區",
      "publish_duration" : "2014-05-26/2014-05-27",
      "publish_from" : "2014-05-26",
      "publish_until" : "2014-05-27",
      "telephone" : "04-26312127"
   },
   {
      "area" : "【區域1】屏東縣恆春鎮鵝鑾里一帶",
      "interval_from" : "2014-05-27T09:00+08",
      "interval_until" : "2014-05-27T17:00+08",
      "publish_area" : "946屏東縣恆春鎮",
      "publish_duration" : "2014-05-26/2014-05-28",
      "publish_from" : "2014-05-26",
      "publish_until" : "2014-05-28",
      "telephone" : "088892256"
   },
   {
      "area" : "【區域1】苗栗縣大湖鄉水尾坪;苗栗縣泰安鄉清安村",
      "interval_from" : "2014-05-26T14:00+08",
      "interval_until" : "2014-05-26T19:00+08",
      "publish_area" : "364苗栗縣大湖鄉     365苗栗縣泰安鄉",
      "publish_duration" : "2014-05-26/2014-05-27",
      "publish_from" : "2014-05-26",
      "publish_until" : "2014-05-27",
      "telephone" : "037991026"
   },
   {
      "area" : "【區域1】台南市玉井區大成路",
      "interval_from" : "2014-05-26T11:00+08",
      "interval_until" : "2014-05-26T13:00+08",
      "publish_area" : "714台南市玉井區",
      "publish_duration" : "2014-05-26/2014-05-27",
      "publish_from" : "2014-05-26",
      "publish_until" : "2014-05-27",
      "telephone" : "06-5742323"
   },
   {
      "area" : "【區域1】台中市太平區新福路以東.振英街以西.振武路以南.新福16街以北.",
      "interval_from" : "2014-05-26T11:15+08",
      "interval_until" : "2014-05-26T18:00+08",
      "publish_area" : "411台中市太平區",
      "publish_duration" : "2014-05-26/2014-05-27",
      "publish_from" : "2014-05-26",
      "publish_until" : "2014-05-27",
      "telephone" : "24821831 . 24820158"
   },
   {
      "area" : "【區域1】台中市西屯區工業三十五路〈31號〉附近一帶‧",
      "interval_from" : "2014-05-26T09:10+08",
      "interval_until" : "2014-05-26T14:10+08",
      "publish_area" : "407台中市西屯區",
      "publish_duration" : "2014-05-26/2014-05-27",
      "publish_from" : "2014-05-26",
      "publish_until" : "2014-05-27",
      "telephone" : "22442469、1910"
   },
   {
      "area" : "【區域1】南投縣國姓鄉石門村，國姓村，柑林村",
      "interval_from" : "2014-05-26T12:00+08",
      "interval_until" : "2014-05-26T17:00+08",
      "publish_area" : "544南投縣國姓鄉",
      "publish_duration" : "2014-05-26/2014-05-27",
      "publish_from" : "2014-05-26",
      "publish_until" : "2014-05-27",
      "telephone" : "049-2915176"
   },
   {
      "area" : "【區域1】嘉義市西區保生里通化二街、通化三街、通化四街等所有住戶",
      "interval_comment" : "每日上午8點至下午6點(管線末端用戶至下午8點)",
      "interval_from" : "2014-05-28T08:00+08",
      "interval_until" : "2014-06-06T18:00+08",
      "publish_area" : "600嘉義市西區",
      "publish_duration" : "2014-05-26/2014-06-07",
      "publish_from" : "2014-05-26",
      "publish_until" : "2014-06-07",
      "telephone" : "05-2252670轉252"
   }
]
